{
  "project_info": {
    "project_number": "402113228442",
    "firebase_url": "https://magicapp-e90a5.firebaseio.com",
    "project_id": "magicapp-e90a5",
    "storage_bucket": "magicapp-e90a5.appspot.com"
  },
  "client": [
    {
      "client_info": {
        "mobilesdk_app_id": "1:402113228442:android:c89c40f421a4b2f7",
        "android_client_info": {
          "package_name": "com.chordhalper"
        }
      },
      "oauth_client": [
        {
          "client_id": "402113228442-c781pj1td7l9nou8gd6vr10f8esu342a.apps.googleusercontent.com",
          "client_type": 3
        }
      ],
      "api_key": [
        {
          "current_key": "AIzaSyAqCsKxwHPnwHR4yAaO8MHYh4af5Sy5yLc"
        }
      ],
      "services": {
        "appinvite_service": {
          "other_platform_oauth_client": [
            {
              "client_id": "402113228442-c781pj1td7l9nou8gd6vr10f8esu342a.apps.googleusercontent.com",
              "client_type": 3
            }
          ]
        }
      }
    }
  ],
  "configuration_version": "1"
}